LICENSE.txt
README.rst
setup.py
AlgorumQuantClient/__init__.py
AlgorumQuantClient/algorum_types.py
AlgorumQuantClient/concurrent_collections.py
AlgorumQuantClient/quant_client.py
AlgorumQuantClient/remote_indicator_evaluator.py
algorum_quant_client_py3.egg-info/PKG-INFO
algorum_quant_client_py3.egg-info/SOURCES.txt
algorum_quant_client_py3.egg-info/dependency_links.txt
algorum_quant_client_py3.egg-info/top_level.txt