Metadata-Version: 2.1
Name: algorum-quant-client-py3
Version: 1.0.38
Summary: Algorum Quant Client Package
Home-page: https://github.com/algorum/AlgorumQuantClientPython3
Author: Adityanand Pasumarthi
Author-email: aditya.pasumarthi@algorum.in
License: MIT
Platform: UNKNOWN
License-File: LICENSE.txt
